{
  "milovana_id": 60625,
  "title": "Mistress Maya's Memory Game",
  "author": "javatex824",
  "rating": 3.2,
  "views": 23935,
  "date": "10/21/2022",
  "thumbnail_hash": "6d6ca9656ccf6fa1d9d54d1689cc27f8d9b22363",
  "tease_type": "eos",
  "tags": [
    "cbt",
    "female-top",
    "for-guys",
    "forced-orgasms",
    "orgasm-denial"
  ],
  "page_count": 27,
  "command_count": 174,
  "media_image_count": 18,
  "media_audio_count": 0,
  "media_file_size": 0,
  "has_audio": false,
  "has_storage": false,
  "has_notifications": false,
  "has_timers": true,
  "has_prompts": false,
  "has_eval": false,
  "playtime_min_seconds": 169,
  "playtime_max_seconds": 826,
  "scraped_at": "2026-05-29T18:48:53.774450518+00:00"
}