{
  "milovana_id": 79624,
  "title": "耐力挑战",
  "author": "2058004835",
  "rating": 3.8,
  "views": 31966,
  "date": "01/16/2026",
  "thumbnail_hash": "b68c33747cbe3d5ffe0d72faa2023d9bfe745523",
  "tease_type": "eos",
  "tags": [
    "cbt",
    "female-top",
    "for-guys",
    "forced-orgasms",
    "orgasm-denial"
  ],
  "page_count": 8,
  "command_count": 353,
  "media_image_count": 329,
  "media_audio_count": 10,
  "media_file_size": 2619581,
  "has_audio": true,
  "has_storage": true,
  "has_notifications": true,
  "has_timers": true,
  "has_prompts": false,
  "has_eval": true,
  "playtime_min_seconds": 663,
  "playtime_max_seconds": 12370,
  "scraped_at": "2026-05-29T20:47:48.138145406+00:00"
}