{
  "milovana_id": 70711,
  "title": "Blackmail Timer",
  "author": "Klaudia",
  "rating": 4.7,
  "views": 67295,
  "date": "07/04/2024",
  "thumbnail_hash": "55e32d373285b8e4c3c13c3b3a9605ae4074193c",
  "tease_type": "eos",
  "tags": [
    "female-top",
    "for-gals",
    "for-guys",
    "verbal-humiliation"
  ],
  "page_count": 37,
  "command_count": 930,
  "media_image_count": 87,
  "media_audio_count": 2,
  "media_file_size": 5780508,
  "has_audio": true,
  "has_storage": false,
  "has_notifications": true,
  "has_timers": true,
  "has_prompts": true,
  "has_eval": true,
  "playtime_min_seconds": 143,
  "playtime_max_seconds": 1333,
  "scraped_at": "2026-05-29T18:48:53.774450518+00:00"
}