{
  "milovana_id": 61055,
  "title": "Ride your pillow",
  "author": "galaktic75",
  "rating": 3.7,
  "views": 22383,
  "date": "11/13/2022",
  "thumbnail_hash": "9c7b0e0e8df1d2498bd62da829447aaafa912ddf",
  "tease_type": "eos",
  "tags": [
    "exercise",
    "for-guys",
    "male-top"
  ],
  "page_count": 41,
  "command_count": 184,
  "media_image_count": 0,
  "media_audio_count": 5,
  "media_file_size": 25047036,
  "has_audio": true,
  "has_storage": false,
  "has_notifications": true,
  "has_timers": true,
  "has_prompts": false,
  "has_eval": false,
  "playtime_min_seconds": 616,
  "playtime_max_seconds": 616,
  "scraped_at": "2026-05-29T20:47:48.138145406+00:00"
}