{
  "milovana_id": 44799,
  "title": "Celebrity Stroke Gauntlet",
  "author": "PoetBird",
  "rating": 2.8,
  "views": 17938,
  "date": "04/02/2020",
  "thumbnail_hash": "2939eb67761e6f14039f73ac6d549483bde8f1f3",
  "tease_type": "eos",
  "tags": [
    "for-guys",
    "forced-orgasms"
  ],
  "page_count": 229,
  "command_count": 698,
  "media_image_count": 233,
  "media_audio_count": 12,
  "media_file_size": 2579770,
  "has_audio": true,
  "has_storage": false,
  "has_notifications": false,
  "has_timers": true,
  "has_prompts": false,
  "has_eval": false,
  "playtime_min_seconds": 4655,
  "playtime_max_seconds": 4655,
  "scraped_at": "2026-05-29T18:48:53.774450518+00:00"
}