{
  "milovana_id": 59685,
  "title": "Mosquito Game by Mistress Denial",
  "author": "mandree99",
  "rating": 2.8,
  "views": 25854,
  "date": "09/14/2022",
  "thumbnail_hash": "0df42f90b6f9f45b8e1f4434939800b086b48008",
  "tease_type": "eos",
  "tags": [
    "cbt",
    "female-top",
    "for-guys",
    "forced-orgasms",
    "orgasm-denial"
  ],
  "page_count": 12,
  "command_count": 154,
  "media_image_count": 141,
  "media_audio_count": 4,
  "media_file_size": 19285022,
  "has_audio": true,
  "has_storage": true,
  "has_notifications": true,
  "has_timers": true,
  "has_prompts": false,
  "has_eval": true,
  "playtime_min_seconds": 45,
  "playtime_max_seconds": 46,
  "scraped_at": "2026-05-29T19:27:38.490962216+00:00"
}