{
  "milovana_id": 59880,
  "title": "The Checkup",
  "author": "officialreal",
  "rating": 4.3,
  "views": 66728,
  "date": "09/13/2022",
  "thumbnail_hash": "76cdef1b70e6d824d451518ec57b568ad052c0c6",
  "tease_type": "eos",
  "tags": [
    "exhibitionism",
    "female-top",
    "for-guys",
    "forced-orgasms",
    "orgasm-denial"
  ],
  "page_count": 36,
  "command_count": 768,
  "media_image_count": 125,
  "media_audio_count": 13,
  "media_file_size": 39663918,
  "has_audio": true,
  "has_storage": false,
  "has_notifications": false,
  "has_timers": true,
  "has_prompts": false,
  "has_eval": true,
  "playtime_min_seconds": 1192,
  "playtime_max_seconds": 1978,
  "scraped_at": "2026-05-29T18:48:53.774450518+00:00"
}