{
  "milovana_id": 41453,
  "title": "Brutal Hentai Edging Lottery Eos Version",
  "author": "FootlongSub",
  "rating": 4.7,
  "views": 333694,
  "date": "09/07/2019",
  "thumbnail_hash": "07579a9526999a340c76a68ccd37aaa7c73eb2d1",
  "tease_type": "eos",
  "tags": [
    "anal",
    "cbt",
    "chastity",
    "female-top",
    "for-guys"
  ],
  "page_count": 404,
  "command_count": 5274,
  "media_image_count": 664,
  "media_audio_count": 3,
  "media_file_size": 12567839,
  "has_audio": true,
  "has_storage": true,
  "has_notifications": true,
  "has_timers": true,
  "has_prompts": true,
  "has_eval": true,
  "playtime_min_seconds": 152,
  "playtime_max_seconds": 2986,
  "scraped_at": "2026-05-29T19:27:38.490962216+00:00"
}