{
  "milovana_id": 75161,
  "title": "猜數字？",
  "author": "Amb",
  "rating": 3.7,
  "views": 31712,
  "date": "03/29/2025",
  "thumbnail_hash": "707ac1cb2d4168711c2b160044e68bd509f3bc19",
  "tease_type": "eos",
  "tags": [
    "female-top",
    "for-guys",
    "kneeling"
  ],
  "page_count": 16,
  "command_count": 230,
  "media_image_count": 0,
  "media_audio_count": 0,
  "media_file_size": 1917474,
  "has_audio": true,
  "has_storage": true,
  "has_notifications": true,
  "has_timers": true,
  "has_prompts": true,
  "has_eval": true,
  "playtime_min_seconds": 117,
  "playtime_max_seconds": 427,
  "scraped_at": "2026-05-29T19:27:38.490962216+00:00"
}