{
  "milovana_id": 68223,
  "title": "Furry Femdom: Renamon",
  "author": "Axolotl",
  "rating": 4.0,
  "views": 10379,
  "date": "12/26/2023",
  "thumbnail_hash": "e85b9ed6a56c381375f30cb6d57709b5b7532935",
  "tease_type": "eos",
  "tags": [
    "for-guys"
  ],
  "page_count": 13,
  "command_count": 228,
  "media_image_count": 31,
  "media_audio_count": 0,
  "media_file_size": 0,
  "has_audio": true,
  "has_storage": false,
  "has_notifications": true,
  "has_timers": true,
  "has_prompts": false,
  "has_eval": false,
  "playtime_min_seconds": 1113,
  "playtime_max_seconds": 1259,
  "scraped_at": "2026-05-29T20:47:48.138145406+00:00"
}