{
  "milovana_id": 48419,
  "title": "Sissification and Bi-Confusion",
  "author": "pullups4me",
  "rating": 4.1,
  "views": 78430,
  "date": "01/08/2021",
  "thumbnail_hash": "6596717b7ec7d8e7cbef13f1939876f39afb299f",
  "tease_type": "eos",
  "tags": [
    "feminization",
    "for-gals",
    "for-guys"
  ],
  "page_count": 24,
  "command_count": 96,
  "media_image_count": 47,
  "media_audio_count": 0,
  "media_file_size": 3507363,
  "has_audio": false,
  "has_storage": false,
  "has_notifications": false,
  "has_timers": true,
  "has_prompts": false,
  "has_eval": false,
  "playtime_min_seconds": 862,
  "playtime_max_seconds": 872,
  "scraped_at": "2026-05-29T19:27:38.490962216+00:00"
}